[
  {
    "name": "Application Start",
    "start": 1599489079849,
    "end": 1599489080507,
    "duration": 658,
    "pid": 8621,
    "index": 0
  },
  {
    "name": "Load Plugin",
    "start": 1599489079852,
    "end": 1599489079864,
    "duration": 12,
    "pid": 8621,
    "index": 1
  },
  {
    "name": "Load Config",
    "start": 1599489079864,
    "end": 1599489079881,
    "duration": 17,
    "pid": 8621,
    "index": 2
  },
  {
    "name": "Require(0) config/config.default.js",
    "start": 1599489079864,
    "end": 1599489079864,
    "duration": 0,
    "pid": 8621,
    "index": 3
  },
  {
    "name": "Require(1) node_modules/egg-session/config/config.default.js",
    "start": 1599489079866,
    "end": 1599489079866,
    "duration": 0,
    "pid": 8621,
    "index": 4
  },
  {
    "name": "Require(2) node_modules/egg-security/config/config.default.js",
    "start": 1599489079866,
    "end": 1599489079867,
    "duration": 1,
    "pid": 8621,
    "index": 5
  },
  {
    "name": "Require(3) node_modules/egg-jsonp/config/config.default.js",
    "start": 1599489079867,
    "end": 1599489079867,
    "duration": 0,
    "pid": 8621,
    "index": 6
  },
  {
    "name": "Require(4) node_modules/egg-onerror/config/config.default.js",
    "start": 1599489079868,
    "end": 1599489079868,
    "duration": 0,
    "pid": 8621,
    "index": 7
  },
  {
    "name": "Require(5) node_modules/egg-i18n/config/config.default.js",
    "start": 1599489079868,
    "end": 1599489079869,
    "duration": 1,
    "pid": 8621,
    "index": 8
  },
  {
    "name": "Require(6) node_modules/egg-watcher/config/config.default.js",
    "start": 1599489079869,
    "end": 1599489079869,
    "duration": 0,
    "pid": 8621,
    "index": 9
  },
  {
    "name": "Require(7) node_modules/egg-schedule/config/config.default.js",
    "start": 1599489079870,
    "end": 1599489079870,
    "duration": 0,
    "pid": 8621,
    "index": 10
  },
  {
    "name": "Require(8) node_modules/egg-multipart/config/config.default.js",
    "start": 1599489079870,
    "end": 1599489079870,
    "duration": 0,
    "pid": 8621,
    "index": 11
  },
  {
    "name": "Require(9) node_modules/egg-development/config/config.default.js",
    "start": 1599489079871,
    "end": 1599489079871,
    "duration": 0,
    "pid": 8621,
    "index": 12
  },
  {
    "name": "Require(10) node_modules/egg-logrotator/config/config.default.js",
    "start": 1599489079871,
    "end": 1599489079872,
    "duration": 1,
    "pid": 8621,
    "index": 13
  },
  {
    "name": "Require(11) node_modules/egg-static/config/config.default.js",
    "start": 1599489079872,
    "end": 1599489079872,
    "duration": 0,
    "pid": 8621,
    "index": 14
  },
  {
    "name": "Require(12) node_modules/egg-view/config/config.default.js",
    "start": 1599489079872,
    "end": 1599489079873,
    "duration": 1,
    "pid": 8621,
    "index": 15
  },
  {
    "name": "Require(13) node_modules/egg-validate/config/config.default.js",
    "start": 1599489079873,
    "end": 1599489079873,
    "duration": 0,
    "pid": 8621,
    "index": 16
  },
  {
    "name": "Require(14) node_modules/egg-view-ejs/config/config.default.js",
    "start": 1599489079873,
    "end": 1599489079874,
    "duration": 1,
    "pid": 8621,
    "index": 17
  },
  {
    "name": "Require(15) node_modules/egg-mysql/config/config.default.js",
    "start": 1599489079874,
    "end": 1599489079875,
    "duration": 1,
    "pid": 8621,
    "index": 18
  },
  {
    "name": "Require(16) node_modules/egg-sequelize/config/config.default.js",
    "start": 1599489079875,
    "end": 1599489079875,
    "duration": 0,
    "pid": 8621,
    "index": 19
  },
  {
    "name": "Require(17) node_modules/egg-jwt/config/config.default.js",
    "start": 1599489079875,
    "end": 1599489079876,
    "duration": 1,
    "pid": 8621,
    "index": 20
  },
  {
    "name": "Require(18) node_modules/egg-redis/config/config.default.js",
    "start": 1599489079876,
    "end": 1599489079876,
    "duration": 0,
    "pid": 8621,
    "index": 21
  },
  {
    "name": "Require(19) node_modules/egg/config/config.default.js",
    "start": 1599489079876,
    "end": 1599489079877,
    "duration": 1,
    "pid": 8621,
    "index": 22
  },
  {
    "name": "Require(20) config/config.default.js",
    "start": 1599489079878,
    "end": 1599489079878,
    "duration": 0,
    "pid": 8621,
    "index": 23
  },
  {
    "name": "Require(21) node_modules/egg-security/config/config.local.js",
    "start": 1599489079878,
    "end": 1599489079878,
    "duration": 0,
    "pid": 8621,
    "index": 24
  },
  {
    "name": "Require(22) node_modules/egg-watcher/config/config.local.js",
    "start": 1599489079879,
    "end": 1599489079879,
    "duration": 0,
    "pid": 8621,
    "index": 25
  },
  {
    "name": "Require(23) node_modules/egg-view/config/config.local.js",
    "start": 1599489079880,
    "end": 1599489079880,
    "duration": 0,
    "pid": 8621,
    "index": 26
  },
  {
    "name": "Require(24) node_modules/egg-view-ejs/config/config.local.js",
    "start": 1599489079880,
    "end": 1599489079880,
    "duration": 0,
    "pid": 8621,
    "index": 27
  },
  {
    "name": "Require(25) node_modules/egg/config/config.local.js",
    "start": 1599489079881,
    "end": 1599489079881,
    "duration": 0,
    "pid": 8621,
    "index": 28
  },
  {
    "name": "Load extend/application.js",
    "start": 1599489079882,
    "end": 1599489079910,
    "duration": 28,
    "pid": 8621,
    "index": 29
  },
  {
    "name": "Require(26) node_modules/egg-session/app/extend/application.js",
    "start": 1599489079882,
    "end": 1599489079883,
    "duration": 1,
    "pid": 8621,
    "index": 30
  },
  {
    "name": "Require(27) node_modules/egg-security/app/extend/application.js",
    "start": 1599489079883,
    "end": 1599489079883,
    "duration": 0,
    "pid": 8621,
    "index": 31
  },
  {
    "name": "Require(28) node_modules/egg-jsonp/app/extend/application.js",
    "start": 1599489079884,
    "end": 1599489079884,
    "duration": 0,
    "pid": 8621,
    "index": 32
  },
  {
    "name": "Require(29) node_modules/egg-logrotator/app/extend/application.js",
    "start": 1599489079885,
    "end": 1599489079885,
    "duration": 0,
    "pid": 8621,
    "index": 33
  },
  {
    "name": "Require(30) node_modules/egg-view/app/extend/application.js",
    "start": 1599489079886,
    "end": 1599489079886,
    "duration": 0,
    "pid": 8621,
    "index": 34
  },
  {
    "name": "Require(31) node_modules/egg-jwt/app/extend/application.js",
    "start": 1599489079887,
    "end": 1599489079907,
    "duration": 20,
    "pid": 8621,
    "index": 35
  },
  {
    "name": "Require(32) app/extend/application.js",
    "start": 1599489079907,
    "end": 1599489079908,
    "duration": 1,
    "pid": 8621,
    "index": 36
  },
  {
    "name": "Load extend/request.js",
    "start": 1599489079910,
    "end": 1599489079914,
    "duration": 4,
    "pid": 8621,
    "index": 37
  },
  {
    "name": "Require(33) node_modules/egg/app/extend/request.js",
    "start": 1599489079912,
    "end": 1599489079912,
    "duration": 0,
    "pid": 8621,
    "index": 38
  },
  {
    "name": "Require(34) app/extend/request.js",
    "start": 1599489079912,
    "end": 1599489079913,
    "duration": 1,
    "pid": 8621,
    "index": 39
  },
  {
    "name": "Load extend/response.js",
    "start": 1599489079914,
    "end": 1599489079919,
    "duration": 5,
    "pid": 8621,
    "index": 40
  },
  {
    "name": "Require(35) node_modules/egg/app/extend/response.js",
    "start": 1599489079915,
    "end": 1599489079918,
    "duration": 3,
    "pid": 8621,
    "index": 41
  },
  {
    "name": "Require(36) app/extend/response.js",
    "start": 1599489079918,
    "end": 1599489079918,
    "duration": 0,
    "pid": 8621,
    "index": 42
  },
  {
    "name": "Load extend/context.js",
    "start": 1599489079920,
    "end": 1599489079957,
    "duration": 37,
    "pid": 8621,
    "index": 43
  },
  {
    "name": "Require(37) node_modules/egg-security/app/extend/context.js",
    "start": 1599489079920,
    "end": 1599489079924,
    "duration": 4,
    "pid": 8621,
    "index": 44
  },
  {
    "name": "Require(38) node_modules/egg-jsonp/app/extend/context.js",
    "start": 1599489079924,
    "end": 1599489079925,
    "duration": 1,
    "pid": 8621,
    "index": 45
  },
  {
    "name": "Require(39) node_modules/egg-i18n/app/extend/context.js",
    "start": 1599489079925,
    "end": 1599489079925,
    "duration": 0,
    "pid": 8621,
    "index": 46
  },
  {
    "name": "Require(40) node_modules/egg-multipart/app/extend/context.js",
    "start": 1599489079925,
    "end": 1599489079953,
    "duration": 28,
    "pid": 8621,
    "index": 47
  },
  {
    "name": "Require(41) node_modules/egg-view/app/extend/context.js",
    "start": 1599489079953,
    "end": 1599489079954,
    "duration": 1,
    "pid": 8621,
    "index": 48
  },
  {
    "name": "Require(42) node_modules/egg-validate/app/extend/context.js",
    "start": 1599489079954,
    "end": 1599489079954,
    "duration": 0,
    "pid": 8621,
    "index": 49
  },
  {
    "name": "Require(43) lib/plugin/egg-info/app/extend/context.js",
    "start": 1599489079954,
    "end": 1599489079955,
    "duration": 1,
    "pid": 8621,
    "index": 50
  },
  {
    "name": "Require(44) node_modules/egg/app/extend/context.js",
    "start": 1599489079955,
    "end": 1599489079955,
    "duration": 0,
    "pid": 8621,
    "index": 51
  },
  {
    "name": "Require(45) app/extend/context.js",
    "start": 1599489079956,
    "end": 1599489079956,
    "duration": 0,
    "pid": 8621,
    "index": 52
  },
  {
    "name": "Load extend/helper.js",
    "start": 1599489079957,
    "end": 1599489079970,
    "duration": 13,
    "pid": 8621,
    "index": 53
  },
  {
    "name": "Require(46) node_modules/egg-security/app/extend/helper.js",
    "start": 1599489079957,
    "end": 1599489079967,
    "duration": 10,
    "pid": 8621,
    "index": 54
  },
  {
    "name": "Require(47) node_modules/egg/app/extend/helper.js",
    "start": 1599489079968,
    "end": 1599489079968,
    "duration": 0,
    "pid": 8621,
    "index": 55
  },
  {
    "name": "Require(48) app/extend/helper.js",
    "start": 1599489079968,
    "end": 1599489079969,
    "duration": 1,
    "pid": 8621,
    "index": 56
  },
  {
    "name": "Load app.js",
    "start": 1599489079970,
    "end": 1599489080001,
    "duration": 31,
    "pid": 8621,
    "index": 57
  },
  {
    "name": "Require(49) node_modules/egg-session/app.js",
    "start": 1599489079971,
    "end": 1599489079971,
    "duration": 0,
    "pid": 8621,
    "index": 58
  },
  {
    "name": "Require(50) node_modules/egg-security/app.js",
    "start": 1599489079971,
    "end": 1599489079972,
    "duration": 1,
    "pid": 8621,
    "index": 59
  },
  {
    "name": "Require(51) node_modules/egg-onerror/app.js",
    "start": 1599489079972,
    "end": 1599489079978,
    "duration": 6,
    "pid": 8621,
    "index": 60
  },
  {
    "name": "Require(52) node_modules/egg-i18n/app.js",
    "start": 1599489079978,
    "end": 1599489079985,
    "duration": 7,
    "pid": 8621,
    "index": 61
  },
  {
    "name": "Require(53) node_modules/egg-watcher/app.js",
    "start": 1599489079985,
    "end": 1599489079986,
    "duration": 1,
    "pid": 8621,
    "index": 62
  },
  {
    "name": "Require(54) node_modules/egg-schedule/app.js",
    "start": 1599489079987,
    "end": 1599489079987,
    "duration": 0,
    "pid": 8621,
    "index": 63
  },
  {
    "name": "Require(55) node_modules/egg-multipart/app.js",
    "start": 1599489079987,
    "end": 1599489079989,
    "duration": 2,
    "pid": 8621,
    "index": 64
  },
  {
    "name": "Require(56) node_modules/egg-development/app.js",
    "start": 1599489079989,
    "end": 1599489079989,
    "duration": 0,
    "pid": 8621,
    "index": 65
  },
  {
    "name": "Require(57) node_modules/egg-logrotator/app.js",
    "start": 1599489079989,
    "end": 1599489079989,
    "duration": 0,
    "pid": 8621,
    "index": 66
  },
  {
    "name": "Require(58) node_modules/egg-static/app.js",
    "start": 1599489079989,
    "end": 1599489079990,
    "duration": 1,
    "pid": 8621,
    "index": 67
  },
  {
    "name": "Require(59) node_modules/egg-validate/app.js",
    "start": 1599489079990,
    "end": 1599489079991,
    "duration": 1,
    "pid": 8621,
    "index": 68
  },
  {
    "name": "Require(60) node_modules/egg-view-ejs/app.js",
    "start": 1599489079991,
    "end": 1599489079991,
    "duration": 0,
    "pid": 8621,
    "index": 69
  },
  {
    "name": "Require(61) node_modules/egg-mysql/app.js",
    "start": 1599489079992,
    "end": 1599489079999,
    "duration": 7,
    "pid": 8621,
    "index": 70
  },
  {
    "name": "Require(62) node_modules/egg-sequelize/app.js",
    "start": 1599489079999,
    "end": 1599489079999,
    "duration": 0,
    "pid": 8621,
    "index": 71
  },
  {
    "name": "Require(63) node_modules/egg-jwt/app.js",
    "start": 1599489079999,
    "end": 1599489080000,
    "duration": 1,
    "pid": 8621,
    "index": 72
  },
  {
    "name": "Require(64) node_modules/egg-redis/app.js",
    "start": 1599489080000,
    "end": 1599489080000,
    "duration": 0,
    "pid": 8621,
    "index": 73
  },
  {
    "name": "Require(65) app.js",
    "start": 1599489080001,
    "end": 1599489080001,
    "duration": 0,
    "pid": 8621,
    "index": 74
  },
  {
    "name": "Before Start in node_modules/egg-watcher/lib/init.js:15:14",
    "start": 1599489080007,
    "end": 1599489080468,
    "duration": 461,
    "pid": 8621,
    "index": 75
  },
  {
    "name": "Before Start in node_modules/egg-mysql/lib/mysql.js:20:7",
    "start": 1599489080083,
    "end": 1599489080485,
    "duration": 402,
    "pid": 8621,
    "index": 76
  },
  {
    "name": "Load \"Symbol(model)\" to Application",
    "start": 1599489080304,
    "end": 1599489080316,
    "duration": 12,
    "pid": 8621,
    "index": 77
  },
  {
    "name": "Before Start in node_modules/egg-sequelize/lib/loader.js:39:7",
    "start": 1599489080316,
    "end": 1599489080507,
    "duration": 191,
    "pid": 8621,
    "index": 78
  },
  {
    "name": "Before Start in node_modules/egg-redis/lib/redis.js:53:7",
    "start": 1599489080357,
    "end": 1599489080464,
    "duration": 107,
    "pid": 8621,
    "index": 79
  },
  {
    "name": "Load Service",
    "start": 1599489080358,
    "end": 1599489080370,
    "duration": 12,
    "pid": 8621,
    "index": 80
  },
  {
    "name": "Load \"service\" to Context",
    "start": 1599489080358,
    "end": 1599489080370,
    "duration": 12,
    "pid": 8621,
    "index": 81
  },
  {
    "name": "Load Middleware",
    "start": 1599489080370,
    "end": 1599489080424,
    "duration": 54,
    "pid": 8621,
    "index": 82
  },
  {
    "name": "Load \"middlewares\" to Application",
    "start": 1599489080370,
    "end": 1599489080416,
    "duration": 46,
    "pid": 8621,
    "index": 83
  },
  {
    "name": "Load Controller",
    "start": 1599489080424,
    "end": 1599489080427,
    "duration": 3,
    "pid": 8621,
    "index": 84
  },
  {
    "name": "Load \"controller\" to Application",
    "start": 1599489080424,
    "end": 1599489080427,
    "duration": 3,
    "pid": 8621,
    "index": 85
  },
  {
    "name": "Load Router",
    "start": 1599489080427,
    "end": 1599489080429,
    "duration": 2,
    "pid": 8621,
    "index": 86
  },
  {
    "name": "Require(66) app/router.js",
    "start": 1599489080427,
    "end": 1599489080427,
    "duration": 0,
    "pid": 8621,
    "index": 87
  },
  {
    "name": "Before Start in node_modules/egg-core/lib/egg.js:303:10",
    "start": 1599489080428,
    "end": 1599489080448,
    "duration": 20,
    "pid": 8621,
    "index": 88
  }
]